automate_email/__init__.py
automate_email-0.1.0.dist-info/LICENSE
automate_email-0.1.0.dist-info/METADATA
automate_email-0.1.0.dist-info/WHEEL
automate_email-0.1.0.dist-info/top_level.txt
automate_email-0.1.0.dist-info/RECORD
