Metadata-Version: 2.1
Name: automate-email
Version: 0.1.0
Summary: Automate emails with Outlook
Author: Xavier Hilbert
Author-email: xhilbe@gmail.com
Classifier: Programming Language :: Python :: 3
Classifier: License :: OSI Approved :: MIT License
Classifier: Operating System :: Microsoft :: Windows
Requires-Python: >=3.7
License-File: LICENSE
